bengali_bpe/__init__.py
bengali_bpe/encoder.py
bengali_bpe/utils.py
bengali_bpe-0.2.0.dist-info/licenses/LICENSE
bengali_bpe-0.2.0.dist-info/METADATA
bengali_bpe-0.2.0.dist-info/WHEEL
bengali_bpe-0.2.0.dist-info/top_level.txt
bengali_bpe-0.2.0.dist-info/RECORD
