Metadata-Version: 2.4
Name: bengali-bpe
Version: 0.2.0
Summary: A Byte Pair Encoding (BPE) library for the Bengali language.
Author-email: Firoj Ahmmed Patwary <firoj.stat@gmail.com>
License: MIT
Project-URL: Homepage, https://github.com/firojap/bengali_bpe
Project-URL: Repository, https://github.com/firojap/bengali_bpe
Project-URL: Issues, https://github.com/firojap/bengali_bpe/issues
Keywords: bengali,bangla,bpe,tokenization,nlp
Classifier: Programming Language :: Python :: 3
Classifier: License :: OSI Approved :: MIT License
Classifier: Operating System :: OS Independent
Classifier: Natural Language :: Bengali
Classifier: Topic :: Text Processing :: Linguistic
Requires-Python: >=3.8
License-File: LICENSE
Dynamic: license-file
